README.md
setup.cfg
setup.py
chimoney/Account.py
chimoney/Base.py
chimoney/Chimoney.py
chimoney/Errors.py
chimoney/Info.py
chimoney/Payouts.py
chimoney/Redeem.py
chimoney/SubAccount.py
chimoney/Wallet.py
chimoney/__init__.py
chimoney_py.egg-info/PKG-INFO
chimoney_py.egg-info/SOURCES.txt
chimoney_py.egg-info/dependency_links.txt
chimoney_py.egg-info/requires.txt
chimoney_py.egg-info/top_level.txt