Metadata-Version: 2.1
Name: chimoney-py
Version: 0.0.1
Summary: A Python package for Chimoney
Home-page: https://github.com/thelimeskies/chimoney-py
Author: Asikhalaye Samuel
Author-email: samuelasikhalaye@gmail.com
License: MIT
Keywords: Chimoney,Python,Chimoney-Python,Chimoney Python,Chimoney Python Wrapper
Platform: UNKNOWN
Classifier: Programming Language :: Python :: 3
Classifier: License :: OSI Approved :: MIT License
Classifier: Operating System :: OS Independent
Classifier: Development Status :: 3 - Alpha
Classifier: Intended Audience :: Developers
Classifier: Topic :: Software Development :: Libraries :: Python Modules
Classifier: Topic :: Software Development :: Libraries
Classifier: Topic :: Software Development
Classifier: Topic :: Utilities
Classifier: Topic :: Internet
Requires-Python: >=3.6
